{
  "meta": {
    "article_title": "December 11, 2017 - Push-Button Matches - Playing the Scary All-Out Attacker",
    "article_slug": "push_button_matches_playing_the_scary_all_out_attacker",
    "source_url": "http://www.tabletenniscoaching.com/node/2833",
    "date_accessed": "2025-10-15"
  },
  "terminologie_extrait": [],
  "problemes_solutions": {
    "push_button_matches_playing_the_scary_all_out_attacker": [
      {
        "probleme": "Playing the scary all-out attacker",
        "diagnostic": "Not specified by source.",
        "causes_communes": [
          "Opponent attacks everything, no matter what you do"
        ],
        "solutions_progressives": {
          "debutant": [
            "Attack first and look for every chance to attack",
            "Keep the ball deep to make it harder to attack",
            "Vary the spin to throw off the opponent's timing",
            "Push effectively with long pushes that go pretty long"
          ],
          "intermediaire": [],
          "avance": []
        },
        "exercices_complementaires": [
          {
            "nom": "Serve and counter-attack",
            "description": "Attack first, especially on your serve, and force the opponent to go for a wild counter-attack.",
            "difficulte": "Beginner",
            "duree": "Not specified by source.",
            "materiel": "Generic"
          },
          {
            "nom": "Long pushes with last-second changes of direction",
            "description": "Make long pushes that go pretty long, with last-second changes of direction, and be low, heavy (or varied), and somewhat quick.",
            "difficulte": "Beginner",
            "duree": "Not specified by source.",
            "materiel": "Generic"
          }
        ],
        "metriques_progression": [
          {
            "nom": "Rush with your first shot",
            "description": "Get in a quick short and force the opponent to make mistakes."
          },
          {
            "nom": "Place your shots",
            "description": "Go to the wide corners or elbow, depending on the opponent's strengths and weaknesses."
          }
        ],
        "erreurs_a_eviter": [
          "Panic if the opponent makes a few great shots"
        ],
        "source_url": "http://www.tabletenniscoaching.com/node/2833"
      }
    ]
  }
}