{
  "meta": {
    "article_title": "April 23, 2018 - Are You a 10-8 or an 8-10 Player?",
    "article_slug": "are_you_a_10_8_or_an_8_10_player",
    "source_url": "http://www.tabletenniscoaching.com/node/2929",
    "date_accessed": "2025-10-15"
  },
  "terminologie_extrait": [],
  "problemes_solutions": {
    "are_you_a_10_8_or_an_8_10_player": [
      {
        "probleme": "Players' performance variations",
        "diagnostic": "Not specified by source.",
        "causes_communes": [],
        "solutions_progressives": {
          "debutant": [
            "Imagine the score where you play best"
          ],
          "intermediaire": [],
          "avance": []
        },
        "exercices_complementaires": [
          {
            "nom": "Mental technique drill",
            "description": "Imagining the score where you play best, then apply it to your game. Start imagining near the end of the match.",
            "difficulte": "Beginner",
            "duree": "Not specified by source.",
            "materiel": "Mental focus"
          }
        ],
        "metriques_progression": [
          "Play consistently well at any score"
        ],
        "erreurs_a_eviter": [],
        "source_url": "http://www.tabletenniscoaching.com/node/2929"
      }
    ]
  }
}